tri_query/__init__.py
tri_query/db_compat.py
tri_query/templates/tri_query/form.html
tri.query-6.1.0.dist-info/AUTHORS.rst
tri.query-6.1.0.dist-info/LICENSE
tri.query-6.1.0.dist-info/METADATA
tri.query-6.1.0.dist-info/WHEEL
tri.query-6.1.0.dist-info/top_level.txt
tri.query-6.1.0.dist-info/RECORD
