Metadata-Version: 2.1
Name: tri.query
Version: 6.1.0
Summary: tri.query is a library to define queries
Home-page: https://github.com/TriOptima/tri.query
Author: Anders Hovmöller
Author-email: anders.hovmoller@trioptima.com
License: BSD
Keywords: tri.query
Platform: UNKNOWN
Classifier: Development Status :: 5 - Production/Stable
Classifier: Intended Audience :: Developers
Classifier: License :: OSI Approved :: BSD License
Classifier: Natural Language :: English
Classifier: Programming Language :: Python :: 2
Classifier: Programming Language :: Python :: 2.7
Classifier: Programming Language :: Python :: 3
Classifier: Programming Language :: Python :: 3.6
Requires-Dist: Django (>=1.7)
Requires-Dist: tri.declarative (<5.0.0,>=4.0.0)
Requires-Dist: tri.struct (<4.0.0,>=3.0.0)
Requires-Dist: tri.form (<8.0.0,>=7.2.3)
Requires-Dist: pyparsing
